<?xml version="1.0" encoding="utf-8"?>
<LanguageData>

  <ClovenCygorFaction.label>сайгор</ClovenCygorFaction.label>
  <ClovenCygorFaction.labelPlural>сайгоры</ClovenCygorFaction.labelPlural>
  <ClovenCygorFaction.lifeStages.0.label>сайгор</ClovenCygorFaction.lifeStages.0.label>
  <ClovenCygorFaction.lifeStages.0.labelPlural>сайгоры</ClovenCygorFaction.lifeStages.0.labelPlural>
  <ClovenCygorFaction.lifeStages.0.labelMale>сайгор</ClovenCygorFaction.lifeStages.0.labelMale>
  <ClovenCygorFaction.lifeStages.0.labelMalePlural>сайгоры</ClovenCygorFaction.lifeStages.0.labelMalePlural>
  <ClovenCygorFaction.lifeStages.0.labelFemale>сайгор</ClovenCygorFaction.lifeStages.0.labelFemale>
  <ClovenCygorFaction.lifeStages.0.labelFemalePlural>сайгоры</ClovenCygorFaction.lifeStages.0.labelFemalePlural>
  <ClovenCygorFaction.lifeStages.1.label>сайгор</ClovenCygorFaction.lifeStages.1.label>
  <ClovenCygorFaction.lifeStages.1.labelPlural>сайгоры</ClovenCygorFaction.lifeStages.1.labelPlural>
  <ClovenCygorFaction.lifeStages.1.labelMale>сайгор</ClovenCygorFaction.lifeStages.1.labelMale>
  <ClovenCygorFaction.lifeStages.1.labelMalePlural>сайгоры</ClovenCygorFaction.lifeStages.1.labelMalePlural>
  <ClovenCygorFaction.lifeStages.1.labelFemale>сайгор</ClovenCygorFaction.lifeStages.1.labelFemale>
  <ClovenCygorFaction.lifeStages.1.labelFemalePlural>сайгоры</ClovenCygorFaction.lifeStages.1.labelFemalePlural>
  <ClovenCygorFaction.lifeStages.2.label>сайгор</ClovenCygorFaction.lifeStages.2.label>
  <ClovenCygorFaction.lifeStages.2.labelPlural>сайгоры</ClovenCygorFaction.lifeStages.2.labelPlural>
  <ClovenCygorFaction.lifeStages.2.labelMale>сайгор</ClovenCygorFaction.lifeStages.2.labelMale>
  <ClovenCygorFaction.lifeStages.2.labelMalePlural>сайгоры</ClovenCygorFaction.lifeStages.2.labelMalePlural>
  <ClovenCygorFaction.lifeStages.2.labelFemale>сайгор</ClovenCygorFaction.lifeStages.2.labelFemale>
  <ClovenCygorFaction.lifeStages.2.labelFemalePlural>сайгоры</ClovenCygorFaction.lifeStages.2.labelFemalePlural>
  <ClovenCygorFaction.labelMale>сайгор</ClovenCygorFaction.labelMale>
  <ClovenCygorFaction.labelMalePlural>сайгоры</ClovenCygorFaction.labelMalePlural>
  <ClovenCygorFaction.labelFemale>сайгор</ClovenCygorFaction.labelFemale>
  <ClovenCygorFaction.labelFemalePlural>сайгоры</ClovenCygorFaction.labelFemalePlural>


</LanguageData>